setup.py
universalbus/__init__.py
universalbus.egg-info/PKG-INFO
universalbus.egg-info/SOURCES.txt
universalbus.egg-info/dependency_links.txt
universalbus.egg-info/requires.txt
universalbus.egg-info/top_level.txt