Metadata-Version: 1.1
Name: universalbus
Version: 0.0.8
Summary: Universal Bus over rabbitmq.
Home-page: https://github.com/KokocGroup/universal-bus
Author: UNKNOWN
Author-email: UNKNOWN
License: UNKNOWN
Download-URL: https://github.com/KokocGroup/universal-bus/tarball/v0.0.8
Platform: UNKNOWN
